[{"_path":"/modules/researchsoftware/exercise-research-life-cycle","_dir":"researchsoftware","_draft":false,"_partial":false,"_locale":"","title":"Exercise Research Life Cycle","description":"","_type":"markdown","_id":"github:modules:researchsoftware:exercise-research-life-cycle.md","_source":"github","_file":"modules/researchsoftware/exercise-research-life-cycle.md","_extension":"md"},{"_path":"/modules/researchsoftware/research-software","_dir":"researchsoftware","_draft":false,"_partial":false,"_locale":"","title":"Research Software","description":"","_type":"markdown","_id":"github:modules:researchsoftware:research-software.md","_source":"github","_file":"modules/researchsoftware/research-software.md","_extension":"md"}]